ogilo/__init__.py
ogilo/checks.py
ogilo/cli.py
ogilo/io.py
ogilo/types.py
ogilo/utils.py
ogilo/data/handles/illumina-pcr-handles.csv
ogilo/data/handles/sanson2018-pcr-handles.csv
ogilo/data/handles/subramanian2018-pcr-handles.csv
ogilo/data/handles/winston2022-pcr-handles.csv
ogilo_array-0.0.3.dist-info/LICENSE
ogilo_array-0.0.3.dist-info/METADATA
ogilo_array-0.0.3.dist-info/WHEEL
ogilo_array-0.0.3.dist-info/entry_points.txt
ogilo_array-0.0.3.dist-info/top_level.txt
ogilo_array-0.0.3.dist-info/RECORD
