Metadata-Version: 2.2
Name: ogilo-array
Version: 0.0.3
Summary: Automated construction of oligo library sequences for oligo array synthesis.
Author-email: Eachan Johnson <eachan.johnson@crick.ac.uk>
License: MIT License
Project-URL: Homepage, https://github.com/scbirlab/ogilo
Project-URL: Bug Tracker, https://github.com/scbirlab/ogilo/issues
Keywords: biology,bioinformatics,biotechnology,science,assay,sequencing,oligonucleotides,oligos
Classifier: Development Status :: 3 - Alpha
Classifier: Intended Audience :: Science/Research
Classifier: Topic :: Scientific/Engineering :: Bio-Informatics
Classifier: License :: OSI Approved :: MIT License
Classifier: Programming Language :: Python :: 3.8
Classifier: Programming Language :: Python :: 3.9
Classifier: Programming Language :: Python :: 3.10
Classifier: Programming Language :: Python :: 3.11
Classifier: Programming Language :: Python :: 3.12
Classifier: Programming Language :: Python :: 3.13
Classifier: Programming Language :: Python :: 3 :: Only
Requires-Python: >=3.8
License-File: LICENSE
Requires-Dist: nemony
Requires-Dist: streq
Requires-Dist: tqdm
Requires-Dist: pytest
